wavinsentio/__init__.py
wavinsentio/wavinsentio.py
wavinsentio-0.5.4.dist-info/licenses/LICENSE
wavinsentio-0.5.4.dist-info/METADATA
wavinsentio-0.5.4.dist-info/WHEEL
wavinsentio-0.5.4.dist-info/top_level.txt
wavinsentio-0.5.4.dist-info/RECORD
